{
  "generated": "2026-05-31T11:09:16.294Z",
  "train_top5": [
    {
      "config": {
        "sizing": 25,
        "minQuality": 85,
        "pyramiding": 60,
        "leverageMult": 2,
        "leverageThreshold": 86,
        "holdMax": 20,
        "atrStop": 0.4,
        "atrTp2": 7
      },
      "median": 133.77508267781334,
      "worst": 75.61149079848947,
      "avgDD": -5.450925522303982,
      "positive": 4,
      "totalFolds": 4,
      "score": 190.29005485046955
    },
    {
      "config": {
        "sizing": 25,
        "minQuality": 85,
        "pyramiding": 60,
        "leverageMult": 2,
        "leverageThreshold": 88,
        "holdMax": 25,
        "atrStop": 0.4,
        "atrTp2": 7
      },
      "median": 132.25548310835566,
      "worst": 63.564404712940636,
      "avgDD": -5.454531757435949,
      "positive": 4,
      "totalFolds": 4,
      "score": 188.1220478213776
    },
    {
      "config": {
        "sizing": 25,
        "minQuality": 85,
        "pyramiding": 55,
        "leverageMult": 2,
        "leverageThreshold": 88,
        "holdMax": 20,
        "atrStop": 0.4,
        "atrTp2": 7
      },
      "median": 126.26080809042355,
      "worst": 60.39571615875352,
      "avgDD": -5.457316404801714,
      "positive": 4,
      "totalFolds": 4,
      "score": 179.59039599362677
    },
    {
      "config": {
        "sizing": 25,
        "minQuality": 84,
        "pyramiding": 60,
        "leverageMult": 2,
        "leverageThreshold": 89,
        "holdMax": 30,
        "atrStop": 0.4,
        "atrTp2": 6.5
      },
      "median": 125.58452434995245,
      "worst": 61.40412858060081,
      "avgDD": -5.505955233516152,
      "positive": 4,
      "totalFolds": 4,
      "score": 178.5461172385906
    },
    {
      "config": {
        "sizing": 25,
        "minQuality": 86,
        "pyramiding": 60,
        "leverageMult": 2,
        "leverageThreshold": 88,
        "holdMax": 25,
        "atrStop": 0.4,
        "atrTp2": 7.5
      },
      "median": 121.66208468855584,
      "worst": 65.67895103765923,
      "avgDD": -5.498242018184696,
      "positive": 4,
      "totalFolds": 4,
      "score": 172.98214978916658
    }
  ],
  "oos_results": [
    {
      "config": {
        "sizing": 25,
        "minQuality": 85,
        "pyramiding": 60,
        "leverageMult": 2,
        "leverageThreshold": 88,
        "holdMax": 25,
        "atrStop": 0.4,
        "atrTp2": 7
      },
      "train_median": 132.25548310835566,
      "oos_median": 20.54,
      "oos_mean": 21.48,
      "positive": 7,
      "beatBH": 6,
      "yearly": [
        {
          "year": 2018,
          "ret": 1.2582120895583884,
          "dd": -13.273710554683424,
          "trades": 93,
          "bh": -7.009394461420982,
          "excess": 8.26760655097937
        },
        {
          "year": 2019,
          "ret": 7.775370989948397,
          "dd": -11.003846369081717,
          "trades": 103,
          "bh": 28.714795902338295,
          "excess": -20.9394249123899
        },
        {
          "year": 2020,
          "ret": 20.544643599428877,
          "dd": -22.0738547309594,
          "trades": 75,
          "bh": 15.292906541696084,
          "excess": 5.251737057732793
        },
        {
          "year": 2021,
          "ret": 40.31442541953097,
          "dd": -10.127079775584082,
          "trades": 95,
          "bh": 28.793058018340577,
          "excess": 11.521367401190393
        },
        {
          "year": 2022,
          "ret": 13.326875200183954,
          "dd": -12.517141807161705,
          "trades": 35,
          "bh": -19.953050663444415,
          "excess": 33.27992586362837
        },
        {
          "year": 2023,
          "ret": -0.8961608868792607,
          "dd": -12.755070099946126,
          "trades": 95,
          "bh": 24.729487207888678,
          "excess": -25.62564809476794
        },
        {
          "year": 2024,
          "ret": 45.753713821494536,
          "dd": -10.034719122565923,
          "trades": 83,
          "bh": 24.01097627216082,
          "excess": 21.742737549333714
        },
        {
          "year": 2025,
          "ret": 43.73679073382178,
          "dd": -19.750322927949444,
          "trades": 82,
          "bh": 16.64721656672594,
          "excess": 27.089574167095837
        }
      ]
    },
    {
      "config": {
        "sizing": 25,
        "minQuality": 86,
        "pyramiding": 60,
        "leverageMult": 2,
        "leverageThreshold": 88,
        "holdMax": 25,
        "atrStop": 0.4,
        "atrTp2": 7.5
      },
      "train_median": 121.66208468855584,
      "oos_median": 16.74,
      "oos_mean": 23.5,
      "positive": 7,
      "beatBH": 5,
      "yearly": [
        {
          "year": 2018,
          "ret": 7.173541821735243,
          "dd": -13.88424091100687,
          "trades": 89,
          "bh": -7.009394461420982,
          "excess": 14.182936283156224
        },
        {
          "year": 2019,
          "ret": 16.419712246387963,
          "dd": -10.385125953923941,
          "trades": 97,
          "bh": 28.714795902338295,
          "excess": -12.295083655950332
        },
        {
          "year": 2020,
          "ret": -0.14522923968395596,
          "dd": -30.63535930476159,
          "trades": 69,
          "bh": 15.292906541696084,
          "excess": -15.43813578138004
        },
        {
          "year": 2021,
          "ret": 47.567601633194954,
          "dd": -9.632691583462687,
          "trades": 93,
          "bh": 28.793058018340577,
          "excess": 18.774543614854377
        },
        {
          "year": 2022,
          "ret": 16.736046224467852,
          "dd": -10.313765464328958,
          "trades": 34,
          "bh": -19.953050663444415,
          "excess": 36.68909688791227
        },
        {
          "year": 2023,
          "ret": 5.445677277037454,
          "dd": -12.306226576419562,
          "trades": 88,
          "bh": 24.729487207888678,
          "excess": -19.283809930851223
        },
        {
          "year": 2024,
          "ret": 47.86355051974549,
          "dd": -9.020190123096878,
          "trades": 79,
          "bh": 24.01097627216082,
          "excess": 23.852574247584666
        },
        {
          "year": 2025,
          "ret": 46.97643425156963,
          "dd": -19.74361648128689,
          "trades": 80,
          "bh": 16.64721656672594,
          "excess": 30.329217684843687
        }
      ]
    },
    {
      "config": {
        "sizing": 25,
        "minQuality": 84,
        "pyramiding": 60,
        "leverageMult": 2,
        "leverageThreshold": 89,
        "holdMax": 30,
        "atrStop": 0.4,
        "atrTp2": 6.5
      },
      "train_median": 125.58452434995245,
      "oos_median": 16.32,
      "oos_mean": 15.85,
      "positive": 7,
      "beatBH": 6,
      "yearly": [
        {
          "year": 2018,
          "ret": 0.5614394125499372,
          "dd": -13.073858434031195,
          "trades": 103,
          "bh": -7.009394461420982,
          "excess": 7.570833873970919
        },
        {
          "year": 2019,
          "ret": 11.324607433530128,
          "dd": -10.310654167308995,
          "trades": 104,
          "bh": 28.714795902338295,
          "excess": -17.39018846880817
        },
        {
          "year": 2020,
          "ret": 16.322635338579747,
          "dd": -22.785016143927376,
          "trades": 78,
          "bh": 15.292906541696084,
          "excess": 1.0297287968836635
        },
        {
          "year": 2021,
          "ret": 36.00613301859742,
          "dd": -11.783680325177215,
          "trades": 101,
          "bh": 28.793058018340577,
          "excess": 7.21307500025684
        },
        {
          "year": 2022,
          "ret": 13.542240997486969,
          "dd": -12.264507909777429,
          "trades": 35,
          "bh": -19.953050663444415,
          "excess": 33.495291660931386
        },
        {
          "year": 2023,
          "ret": -8.758528623753786,
          "dd": -18.760721321078794,
          "trades": 97,
          "bh": 24.729487207888678,
          "excess": -33.488015831642464
        },
        {
          "year": 2024,
          "ret": 27.005535890494407,
          "dd": -10.504924456757408,
          "trades": 92,
          "bh": 24.01097627216082,
          "excess": 2.994559618333586
        },
        {
          "year": 2025,
          "ret": 30.818452123787928,
          "dd": -19.768022253473234,
          "trades": 84,
          "bh": 16.64721656672594,
          "excess": 14.171235557061987
        }
      ]
    },
    {
      "config": {
        "sizing": 25,
        "minQuality": 85,
        "pyramiding": 60,
        "leverageMult": 2,
        "leverageThreshold": 86,
        "holdMax": 20,
        "atrStop": 0.4,
        "atrTp2": 7
      },
      "train_median": 133.77508267781334,
      "oos_median": 14.93,
      "oos_mean": 20.68,
      "positive": 7,
      "beatBH": 5,
      "yearly": [
        {
          "year": 2018,
          "ret": 9.717228687312288,
          "dd": -12.9012254675054,
          "trades": 93,
          "bh": -7.009394461420982,
          "excess": 16.726623148733267
        },
        {
          "year": 2019,
          "ret": 4.928629064646475,
          "dd": -10.57999963712036,
          "trades": 103,
          "bh": 28.714795902338295,
          "excess": -23.78616683769182
        },
        {
          "year": 2020,
          "ret": 14.930095944377417,
          "dd": -23.159514907052685,
          "trades": 75,
          "bh": 15.292906541696084,
          "excess": -0.36281059731866705
        },
        {
          "year": 2021,
          "ret": 40.36483000075754,
          "dd": -9.495858656874399,
          "trades": 95,
          "bh": 28.793058018340577,
          "excess": 11.571771982416966
        },
        {
          "year": 2022,
          "ret": 12.328892225567522,
          "dd": -12.693495294760531,
          "trades": 35,
          "bh": -19.953050663444415,
          "excess": 32.28194288901194
        },
        {
          "year": 2023,
          "ret": -2.577355759104088,
          "dd": -13.37679679787824,
          "trades": 95,
          "bh": 24.729487207888678,
          "excess": -27.306842966992765
        },
        {
          "year": 2024,
          "ret": 45.56980453315905,
          "dd": -8.419559828235524,
          "trades": 85,
          "bh": 24.01097627216082,
          "excess": 21.55882826099823
        },
        {
          "year": 2025,
          "ret": 40.208184144651305,
          "dd": -19.86568529572995,
          "trades": 83,
          "bh": 16.64721656672594,
          "excess": 23.560967577925364
        }
      ]
    },
    {
      "config": {
        "sizing": 25,
        "minQuality": 85,
        "pyramiding": 55,
        "leverageMult": 2,
        "leverageThreshold": 88,
        "holdMax": 20,
        "atrStop": 0.4,
        "atrTp2": 7
      },
      "train_median": 126.26080809042355,
      "oos_median": 13.38,
      "oos_mean": 17.27,
      "positive": 7,
      "beatBH": 5,
      "yearly": [
        {
          "year": 2018,
          "ret": 1.4251149035293533,
          "dd": -12.805805815248196,
          "trades": 93,
          "bh": -7.009394461420982,
          "excess": 8.434509364950335
        },
        {
          "year": 2019,
          "ret": 1.8222113571157252,
          "dd": -11.11958987730091,
          "trades": 103,
          "bh": 28.714795902338295,
          "excess": -26.89258454522257
        },
        {
          "year": 2020,
          "ret": 13.380485356501516,
          "dd": -22.416958283802295,
          "trades": 75,
          "bh": 15.292906541696084,
          "excess": -1.9124211851945674
        },
        {
          "year": 2021,
          "ret": 36.34939642448544,
          "dd": -10.491631831510471,
          "trades": 95,
          "bh": 28.793058018340577,
          "excess": 7.556338406144864
        },
        {
          "year": 2022,
          "ret": 12.050200605108662,
          "dd": -12.50014799000145,
          "trades": 35,
          "bh": -19.953050663444415,
          "excess": 32.00325126855308
        },
        {
          "year": 2023,
          "ret": -3.9282971786414094,
          "dd": -13.704841444085925,
          "trades": 95,
          "bh": 24.729487207888678,
          "excess": -28.657784386530086
        },
        {
          "year": 2024,
          "ret": 39.003547709964145,
          "dd": -10.148024580560815,
          "trades": 85,
          "bh": 24.01097627216082,
          "excess": 14.992571437803324
        },
        {
          "year": 2025,
          "ret": 38.07087282997445,
          "dd": -19.735293652616384,
          "trades": 83,
          "bh": 16.64721656672594,
          "excess": 21.423656263248507
        }
      ]
    }
  ]
}